[[[], false, "CapitalC5", null, [], null, "text", "t2_5r3xgs9f", false, false, [], false, false, 1583548983, "self.stocks", "https://www.reddit.com/r/stocks/comments/feougx/last_stock_to_complete_my_portfolio/", {}, "feougx", true, false, false, false, true, true, false, "", [], "dark", "text", false, false, true, 15, 0, false, "all_ads", "/r/stocks/comments/feougx/last_stock_to_complete_my_portfolio/", false, 6, 1583548989, 1, "I'm working towards 1-5 yrs profit, so long term stock. Atm my portfolio contains DIS, SWKS, SQ, AMD, TWTR, INCY and NIO. To be clear, for example DIS is about 22% of my portfolio, NIO is 5%.\n\nToday I bought DAL and next week, I'll try to buy MA or V for a big amount. Leaves my account at 850 to spend from 8000. I looked at GILD for 68 rate, but they went up like 13% this week, don't think they'll come close again. Was also checking MRVL at 20.50, but they've also risen 11-12%.\n\nI think my portfolio is already pretty diverse, but any advice on a missing opportunity?\n\nAlso, do you have any tips on MA or V? Atm, I just have a target price for both of them and which one reaches it first is the one I will buy.", true, false, false, "stocks", "t5_2qjfk", 521964, "public", "self", "Last stock to complete my portfolio?", 0, "https://www.reddit.com/r/stocks/comments/feougx/last_stock_to_complete_my_portfolio/", "all_ads", 6, 1583545383.0, {"all_awardings": [], "allow_live_comments": false, "author": "CapitalC5", "author_flair_css_class": null, "author_flair_richtext": [], "author_flair_text": null, "author_flair_type": "text", "author_fullname": "t2_5r3xgs9f", "author_patreon_flair": false, "author_premium": false, "awarders": [], "can_mod_post": false, "contest_mode": false, "created_utc": 1583548983, "domain": "self.stocks", "full_link": "https://www.reddit.com/r/stocks/comments/feougx/last_stock_to_complete_my_portfolio/", "gildings": {}, "id": "feougx", "is_crosspostable": true, "is_meta": false, "is_original_content": false, "is_reddit_media_domain": false, "is_robot_indexable": true, "is_self": true, "is_video": false, "link_flair_background_color": "", "link_flair_richtext": [], "link_flair_text_color": "dark", "link_flair_type": "text", "locked": false, "media_only": false, "no_follow": true, "num_comments": 15, "num_crossposts": 0, "over_18": false, "parent_whitelist_status": "all_ads", "permalink": "/r/stocks/comments/feougx/last_stock_to_complete_my_portfolio/", "pinned": false, "pwls": 6, "retrieved_on": 1583548989, "score": 1, "selftext": "I'm working towards 1-5 yrs profit, so long term stock. Atm my portfolio contains DIS, SWKS, SQ, AMD, TWTR, INCY and NIO. To be clear, for example DIS is about 22% of my portfolio, NIO is 5%.\n\nToday I bought DAL and next week, I'll try to buy MA or V for a big amount. Leaves my account at 850 to spend from 8000. I looked at GILD for 68 rate, but they went up like 13% this week, don't think they'll come close again. Was also checking MRVL at 20.50, but they've also risen 11-12%.\n\nI think my portfolio is already pretty diverse, but any advice on a missing opportunity?\n\nAlso, do you have any tips on MA or V? Atm, I just have a target price for both of them and which one reaches it first is the one I will buy.", "send_replies": true, "spoiler": false, "stickied": false, "subreddit": "stocks", "subreddit_id": "t5_2qjfk", "subreddit_subscribers": 521964, "subreddit_type": "public", "thumbnail": "self", "title": "Last stock to complete my portfolio?", "total_awards_received": 0, "url": "https://www.reddit.com/r/stocks/comments/feougx/last_stock_to_complete_my_portfolio/", "whitelist_status": "all_ads", "wls": 6, "created": 1583545383.0}]]